{
    "escalas": [
        {
            "NOME": "0001PA SEG A QUIN 08:00 AS 18:00 SEX 08:00:00 AS 17:00:00",
            "DESC_ESCALA": "SEG A QUI 08:00 AS 18:00 SEX 08:00 AS 17:00",
            "COD": "1",
            "carga_horaria": "44",
            "tipo_escala": "",
            "TIPO": "SEMANAL",
            "JORNADAS": [
                "45c7dc2e8fa846848ba78135",
                "45c7dc2e8fa846848ba78135",
                "45c7dc2e8fa846848ba78135",
                "45c7dc2e8fa846848ba78135",
                "be2d1897df73498db5d06db7",
                "ID_FOLGA",
                "ID_DSR"
            ],
            "dsr": {
                "ativo": "1",
                "dia_completo": "1",
                "desconto_valor_falta": "1",
                "apuracao": {
                    "semanal": "1"
                }
            },
            "TIPO_HORA_ADICIONAL": "",
            "TIPO_HORA_ADICIONAL_NOTURNO": "",
            "COD_ADICIONAL_NOTURNO": "",
            "excedente_apuracao_semanal": "",
            "deficit_apuracao_semanal": "",
            "excedente_apuracao_mensal": "",
            "deficit_apuracao_mensal": "",
            "key": "1cddfeb42cfd4883903b06b5"
        },
        {
            "NOME": "0002PA SEG A SEX 08:00 AS 17:00 E SAB 08:00 AS 12:00",
            "DESC_ESCALA": "SEG A SEX 08:00 AS 17:00 E SAB 08:00 AS 12:00",
            "COD": "2",
            "carga_horaria": "44",
            "tipo_escala": "",
            "TIPO": "SEMANAL",
            "JORNADAS": [
                "be2d1897df73498db5d06db7",
                "be2d1897df73498db5d06db7",
                "be2d1897df73498db5d06db7",
                "be2d1897df73498db5d06db7",
                "be2d1897df73498db5d06db7",
                "e4285448dbc24cf3b0c8e2c1",
                "ID_DSR"
            ],
            "dsr": {
                "ativo": "1",
                "dia_completo": "1",
                "desconto_valor_falta": "1",
                "apuracao": {
                    "semanal": "1"
                }
            },
            "TIPO_HORA_ADICIONAL": "",
            "TIPO_HORA_ADICIONAL_NOTURNO": "",
            "COD_ADICIONAL_NOTURNO": "",
            "excedente_apuracao_semanal": "",
            "deficit_apuracao_semanal": "",
            "excedente_apuracao_mensal": "",
            "deficit_apuracao_mensal": "",
            "key": "fa7379134535472f9ecf6ee6"
        },
        {
            "NOME": "0003PA SEG A SEX 08:00 AS 17:00",
            "DESC_ESCALA": "SEG A SEX 08:00 AS 17:00",
            "COD": "3",
            "carga_horaria": "40",
            "tipo_escala": "",
            "TIPO": "SEMANAL",
            "JORNADAS": [
                "be2d1897df73498db5d06db7",
                "be2d1897df73498db5d06db7",
                "be2d1897df73498db5d06db7",
                "be2d1897df73498db5d06db7",
                "be2d1897df73498db5d06db7",
                "ID_FOLGA",
                "ID_DSR"
            ],
            "dsr": {
                "ativo": "1",
                "dia_completo": "1",
                "desconto_valor_falta": "1",
                "apuracao": {
                    "semanal": "1"
                }
            },
            "TIPO_HORA_ADICIONAL": "",
            "TIPO_HORA_ADICIONAL_NOTURNO": "",
            "COD_ADICIONAL_NOTURNO": "",
            "excedente_apuracao_semanal": "",
            "deficit_apuracao_semanal": "",
            "excedente_apuracao_mensal": "",
            "deficit_apuracao_mensal": "",
            "key": "05b80592887a42c4a79d5e51"
        },
        {
            "NOME": "0004 SEG A SEX 11:00 AS 20:00 RECIFE",
            "DESC_ESCALA": "SEG A SEX 11:00 AS 20:00 RECIFE",
            "COD": "4",
            "carga_horaria": "0",
            "tipo_escala": "",
            "TIPO": "SEMANAL",
            "JORNADAS": [
                "ID_FOLGA",
                "ID_FOLGA",
                "ID_FOLGA",
                "ID_FOLGA",
                "ID_FOLGA",
                "ID_FOLGA",
                "ID_DSR"
            ],
            "dsr": {
                "ativo": "1",
                "dia_completo": "1",
                "desconto_valor_falta": "1",
                "apuracao": {
                    "semanal": "1"
                }
            },
            "TIPO_HORA_ADICIONAL": "",
            "TIPO_HORA_ADICIONAL_NOTURNO": "",
            "COD_ADICIONAL_NOTURNO": "",
            "excedente_apuracao_semanal": "",
            "deficit_apuracao_semanal": "",
            "excedente_apuracao_mensal": "",
            "deficit_apuracao_mensal": "",
            "key": "93f4081c9302478c88f27433"
        },
        {
            "NOME": "0006PA 12X36 DIURNO",
            "DESC_ESCALA": "0006PA 12X36 DIURNO",
            "COD": "5",
            "carga_horaria": "33",
            "tipo_escala": "",
            "TIPO": "12X36",
            "JORNADAS": [
                "f69879ac6f904fdf8e9d800e",
                "ID_FOLGA",
                "f69879ac6f904fdf8e9d800e",
                "ID_FOLGA",
                "f69879ac6f904fdf8e9d800e",
                "ID_FOLGA",
                "ID_DSR"
            ],
            "dsr": {
                "ativo": "1",
                "dia_completo": "1",
                "desconto_valor_falta": "1",
                "apuracao": {
                    "semanal": "1"
                }
            },
            "TIPO_HORA_ADICIONAL": "",
            "TIPO_HORA_ADICIONAL_NOTURNO": "",
            "COD_ADICIONAL_NOTURNO": "",
            "excedente_apuracao_semanal": "",
            "deficit_apuracao_semanal": "",
            "excedente_apuracao_mensal": "",
            "deficit_apuracao_mensal": "",
            "key": "5a5b5c5881ae463c8faa77ce"
        },
        {
            "NOME": "0007PA 12X36 NOTURNO",
            "DESC_ESCALA": "0007PA 12X36 NOTURNO",
            "COD": "6",
            "carga_horaria": "33",
            "tipo_escala": "",
            "TIPO": "12X36",
            "JORNADAS": [
                "f69879ac6f904fdf8e9d800e",
                "ID_FOLGA",
                "f69879ac6f904fdf8e9d800e",
                "ID_FOLGA",
                "f69879ac6f904fdf8e9d800e",
                "ID_FOLGA",
                "ID_DSR"
            ],
            "dsr": {
                "ativo": "1",
                "dia_completo": "1",
                "desconto_valor_falta": "1",
                "apuracao": {
                    "semanal": "1"
                }
            },
            "TIPO_HORA_ADICIONAL": "",
            "TIPO_HORA_ADICIONAL_NOTURNO": "",
            "COD_ADICIONAL_NOTURNO": "",
            "excedente_apuracao_semanal": "",
            "deficit_apuracao_semanal": "",
            "excedente_apuracao_mensal": "",
            "deficit_apuracao_mensal": "",
            "key": "f199a151f83f4a6283200740"
        },
        {
            "NOME": "0008 SEG A QUI 12:00 AS 22:00 SEX 12:00 AS 21:00",
            "DESC_ESCALA": "0008 SEG A QUI 12:00 AS 22:00 SEX 12:00 AS 21:00",
            "COD": "7",
            "carga_horaria": "44",
            "tipo_escala": "",
            "TIPO": "SEMANAL",
            "JORNADAS": [
                "72d0c1ccc118472889c55f26",
                "72d0c1ccc118472889c55f26",
                "72d0c1ccc118472889c55f26",
                "72d0c1ccc118472889c55f26",
                "b1d8a951b137400f92524984",
                "ID_FOLGA",
                "ID_DSR"
            ],
            "dsr": {
                "ativo": "1",
                "dia_completo": "1",
                "desconto_valor_falta": "1",
                "apuracao": {
                    "semanal": "1"
                }
            },
            "TIPO_HORA_ADICIONAL": "",
            "TIPO_HORA_ADICIONAL_NOTURNO": "",
            "COD_ADICIONAL_NOTURNO": "",
            "excedente_apuracao_semanal": "",
            "deficit_apuracao_semanal": "",
            "excedente_apuracao_mensal": "",
            "deficit_apuracao_mensal": "",
            "key": "33676205226141749573cb5f"
        },
        {
            "NOME": "0009PA 2a 5a 07:00 AS 17:00 / SEX 07:00 AS 16:00",
            "DESC_ESCALA": "0009PA 2a 5a 07:00 AS 17:00 / SEX 07:00 AS 16:00",
            "COD": "8",
            "carga_horaria": "26",
            "tipo_escala": "",
            "TIPO": "SEMANAL",
            "JORNADAS": [
                "2722fcf35e3949839ddb8c7f",
                "ID_FOLGA",
                "ID_FOLGA",
                "2722fcf35e3949839ddb8c7f",
                "f396ad3074fe46a49a038c02",
                "ID_FOLGA",
                "ID_DSR"
            ],
            "dsr": {
                "ativo": "1",
                "dia_completo": "1",
                "desconto_valor_falta": "1",
                "apuracao": {
                    "semanal": "1"
                }
            },
            "TIPO_HORA_ADICIONAL": "",
            "TIPO_HORA_ADICIONAL_NOTURNO": "",
            "COD_ADICIONAL_NOTURNO": "",
            "excedente_apuracao_semanal": "",
            "deficit_apuracao_semanal": "",
            "excedente_apuracao_mensal": "",
            "deficit_apuracao_mensal": "",
            "key": "5d12d881b0704b3c9d7e8db8"
        },
        {
            "NOME": "0010 SEG A QUI 10:00 AS 20:00 SEX 10:00 AS 19:00",
            "DESC_ESCALA": "0010 SEG A QUI 10:00 AS 20:00 SEX 10:00 AS 19:00",
            "COD": "9",
            "carga_horaria": "44",
            "tipo_escala": "",
            "TIPO": "SEMANAL",
            "JORNADAS": [
                "cf36cce7a0aa4d9d94bbe4ae",
                "cf36cce7a0aa4d9d94bbe4ae",
                "cf36cce7a0aa4d9d94bbe4ae",
                "cf36cce7a0aa4d9d94bbe4ae",
                "47a8ee57211c4383996324c1",
                "ID_FOLGA",
                "ID_DSR"
            ],
            "dsr": {
                "ativo": "1",
                "dia_completo": "1",
                "desconto_valor_falta": "1",
                "apuracao": {
                    "semanal": "1"
                }
            },
            "TIPO_HORA_ADICIONAL": "",
            "TIPO_HORA_ADICIONAL_NOTURNO": "",
            "COD_ADICIONAL_NOTURNO": "",
            "excedente_apuracao_semanal": "",
            "deficit_apuracao_semanal": "",
            "excedente_apuracao_mensal": "",
            "deficit_apuracao_mensal": "",
            "key": "bc0ca7c578854ee5aa351375"
        },
        {
            "NOME": "0011 SEG A QUI 09:00 AS 19:00 SEX DAS 09:00 AS 18:00",
            "DESC_ESCALA": "0011 SEG A QUI 09:00 AS 19:00 SEX DAS 09:00 AS 18:00",
            "COD": "10",
            "carga_horaria": "44",
            "tipo_escala": "",
            "TIPO": "SEMANAL",
            "JORNADAS": [
                "4a2157a3d89b4b4f91be4faf",
                "4a2157a3d89b4b4f91be4faf",
                "4a2157a3d89b4b4f91be4faf",
                "4a2157a3d89b4b4f91be4faf",
                "5b0814e9c0c64b70ab6f45ed",
                "ID_FOLGA",
                "ID_DSR"
            ],
            "dsr": {
                "ativo": "1",
                "dia_completo": "1",
                "desconto_valor_falta": "1",
                "apuracao": {
                    "semanal": "1"
                }
            },
            "TIPO_HORA_ADICIONAL": "",
            "TIPO_HORA_ADICIONAL_NOTURNO": "",
            "COD_ADICIONAL_NOTURNO": "",
            "excedente_apuracao_semanal": "",
            "deficit_apuracao_semanal": "",
            "excedente_apuracao_mensal": "",
            "deficit_apuracao_mensal": "",
            "key": "be22525d7be14cce90605027"
        },
        {
            "NOME": "0012 2 a 4 DAS 08:00 AS 14:00:20 e QUI A SEX 09 AS 12",
            "DESC_ESCALA": "0012 2 a 4 DAS 08:00 AS 14:00:20 e QUI A SEX 09 AS 12",
            "COD": "11",
            "carga_horaria": "0",
            "tipo_escala": "",
            "TIPO": "SEMANAL",
            "JORNADAS": [
                "ID_FOLGA",
                "ID_FOLGA",
                "ID_FOLGA",
                "ID_FOLGA",
                "ID_FOLGA",
                "ID_FOLGA",
                "ID_DSR"
            ],
            "dsr": {
                "ativo": "1",
                "dia_completo": "1",
                "desconto_valor_falta": "1",
                "apuracao": {
                    "semanal": "1"
                }
            },
            "TIPO_HORA_ADICIONAL": "",
            "TIPO_HORA_ADICIONAL_NOTURNO": "",
            "COD_ADICIONAL_NOTURNO": "",
            "excedente_apuracao_semanal": "",
            "deficit_apuracao_semanal": "",
            "excedente_apuracao_mensal": "",
            "deficit_apuracao_mensal": "",
            "key": "708901c869b846a9ac7ff7a0"
        },
        {
            "NOME": "0013 SEG A SAB DAS 13:40 AS 20:00",
            "DESC_ESCALA": "0013 SEG A SAB DAS 13:40 AS 20:00",
            "COD": "12",
            "carga_horaria": "32",
            "tipo_escala": "",
            "TIPO": "SEMANAL",
            "JORNADAS": [
                "b3d5188a89fa4d62b8139c66",
                "b3d5188a89fa4d62b8139c66",
                "b3d5188a89fa4d62b8139c66",
                "b3d5188a89fa4d62b8139c66",
                "b3d5188a89fa4d62b8139c66",
                "b3d5188a89fa4d62b8139c66",
                "ID_DSR"
            ],
            "dsr": {
                "ativo": "1",
                "dia_completo": "1",
                "desconto_valor_falta": "1",
                "apuracao": {
                    "semanal": "1"
                }
            },
            "TIPO_HORA_ADICIONAL": "",
            "TIPO_HORA_ADICIONAL_NOTURNO": "",
            "COD_ADICIONAL_NOTURNO": "",
            "excedente_apuracao_semanal": "",
            "deficit_apuracao_semanal": "",
            "excedente_apuracao_mensal": "",
            "deficit_apuracao_mensal": "",
            "key": "3838c21bac3c41b59e03ee4a"
        },
        {
            "NOME": "0014 SEG A SAB DAS 15:40 AS 22:00",
            "DESC_ESCALA": "0014 SEG A SAB DAS 15:40 AS 22:00",
            "COD": "13",
            "carga_horaria": "32",
            "tipo_escala": "",
            "TIPO": "SEMANAL",
            "JORNADAS": [
                "0e471c11bd0544c1bfdbaf05",
                "0e471c11bd0544c1bfdbaf05",
                "0e471c11bd0544c1bfdbaf05",
                "0e471c11bd0544c1bfdbaf05",
                "0e471c11bd0544c1bfdbaf05",
                "0e471c11bd0544c1bfdbaf05",
                "ID_DSR"
            ],
            "dsr": {
                "ativo": "1",
                "dia_completo": "1",
                "desconto_valor_falta": "1",
                "apuracao": {
                    "semanal": "1"
                }
            },
            "TIPO_HORA_ADICIONAL": "",
            "TIPO_HORA_ADICIONAL_NOTURNO": "",
            "COD_ADICIONAL_NOTURNO": "",
            "excedente_apuracao_semanal": "",
            "deficit_apuracao_semanal": "",
            "excedente_apuracao_mensal": "",
            "deficit_apuracao_mensal": "",
            "key": "0b5b07368e2b4ed8957d2c6f"
        },
        {
            "NOME": "0015 SEG A QUI 06:00 AS 16:00 SEX 06:00 AS 15:00",
            "DESC_ESCALA": "0015 SEG A QUI 06:00 AS 16:00 SEX 06:00 AS 15:00",
            "COD": "14",
            "carga_horaria": "44",
            "tipo_escala": "",
            "TIPO": "SEMANAL",
            "JORNADAS": [
                "b6c463aeca3f480aa51e0867",
                "b6c463aeca3f480aa51e0867",
                "b6c463aeca3f480aa51e0867",
                "b6c463aeca3f480aa51e0867",
                "64ffacafeb984663a0b9bbdc",
                "ID_FOLGA",
                "ID_DSR"
            ],
            "dsr": {
                "ativo": "1",
                "dia_completo": "1",
                "desconto_valor_falta": "1",
                "apuracao": {
                    "semanal": "1"
                }
            },
            "TIPO_HORA_ADICIONAL": "",
            "TIPO_HORA_ADICIONAL_NOTURNO": "",
            "COD_ADICIONAL_NOTURNO": "",
            "excedente_apuracao_semanal": "",
            "deficit_apuracao_semanal": "",
            "excedente_apuracao_mensal": "",
            "deficit_apuracao_mensal": "",
            "key": "846e38c70b3b4126b491fed1"
        },
        {
            "NOME": "0016PA SEG A SEX 07:00 AS 17:00",
            "DESC_ESCALA": "0016PA SEG A SEX 07:00 AS 17:00",
            "COD": "15",
            "carga_horaria": "18",
            "tipo_escala": "",
            "TIPO": "SEMANAL",
            "JORNADAS": [
                "2722fcf35e3949839ddb8c7f",
                "ID_FOLGA",
                "ID_FOLGA",
                "ID_FOLGA",
                "2722fcf35e3949839ddb8c7f",
                "ID_FOLGA",
                "ID_DSR"
            ],
            "dsr": {
                "ativo": "1",
                "dia_completo": "1",
                "desconto_valor_falta": "1",
                "apuracao": {
                    "semanal": "1"
                }
            },
            "TIPO_HORA_ADICIONAL": "",
            "TIPO_HORA_ADICIONAL_NOTURNO": "",
            "COD_ADICIONAL_NOTURNO": "",
            "excedente_apuracao_semanal": "",
            "deficit_apuracao_semanal": "",
            "excedente_apuracao_mensal": "",
            "deficit_apuracao_mensal": "",
            "key": "2d10678bd86041579ca42b4f"
        },
        {
            "NOME": "0017 SEG A SEX DAS 14:00 AS 22:00",
            "DESC_ESCALA": "0017 SEG A SEX DAS 14:00 AS 22:00",
            "COD": "16",
            "carga_horaria": "35",
            "tipo_escala": "",
            "TIPO": "SEMANAL",
            "JORNADAS": [
                "6d80ebee92d04220ba66ed63",
                "6d80ebee92d04220ba66ed63",
                "6d80ebee92d04220ba66ed63",
                "6d80ebee92d04220ba66ed63",
                "6d80ebee92d04220ba66ed63",
                "ID_FOLGA",
                "ID_DSR"
            ],
            "dsr": {
                "ativo": "1",
                "dia_completo": "1",
                "desconto_valor_falta": "1",
                "apuracao": {
                    "semanal": "1"
                }
            },
            "TIPO_HORA_ADICIONAL": "",
            "TIPO_HORA_ADICIONAL_NOTURNO": "",
            "COD_ADICIONAL_NOTURNO": "",
            "excedente_apuracao_semanal": "",
            "deficit_apuracao_semanal": "",
            "excedente_apuracao_mensal": "",
            "deficit_apuracao_mensal": "",
            "key": "7175982d049f4f4d83dfae55"
        },
        {
            "NOME": "0018PA SEG A SEX DAS 22:00 AS 06:00",
            "DESC_ESCALA": "0018PA SEG A SEX DAS 22:00 AS 06:00",
            "COD": "17",
            "carga_horaria": "-34",
            "tipo_escala": "",
            "TIPO": "SEMANAL",
            "JORNADAS": [
                "f22d70a867584cfdb6a5bc30",
                "ID_FOLGA",
                "ID_FOLGA",
                "ID_FOLGA",
                "f22d70a867584cfdb6a5bc30",
                "ID_FOLGA",
                "ID_DSR"
            ],
            "dsr": {
                "ativo": "1",
                "dia_completo": "1",
                "desconto_valor_falta": "1",
                "apuracao": {
                    "semanal": "1"
                }
            },
            "TIPO_HORA_ADICIONAL": "",
            "TIPO_HORA_ADICIONAL_NOTURNO": "",
            "COD_ADICIONAL_NOTURNO": "",
            "excedente_apuracao_semanal": "",
            "deficit_apuracao_semanal": "",
            "excedente_apuracao_mensal": "",
            "deficit_apuracao_mensal": "",
            "key": "2c0ac3ce8a384c90a18175ba"
        },
        {
            "NOME": "0019PA SEG A SEX NOTURNO 22:00 AS 06:00",
            "DESC_ESCALA": "0019PA SEG A SEX NOTURNO 22:00 AS 06:00",
            "COD": "18",
            "carga_horaria": "-34",
            "tipo_escala": "",
            "TIPO": "SEMANAL",
            "JORNADAS": [
                "f22d70a867584cfdb6a5bc30",
                "ID_FOLGA",
                "ID_FOLGA",
                "ID_FOLGA",
                "f22d70a867584cfdb6a5bc30",
                "ID_FOLGA",
                "ID_DSR"
            ],
            "dsr": {
                "ativo": "1",
                "dia_completo": "1",
                "desconto_valor_falta": "1",
                "apuracao": {
                    "semanal": "1"
                }
            },
            "TIPO_HORA_ADICIONAL": "",
            "TIPO_HORA_ADICIONAL_NOTURNO": "",
            "COD_ADICIONAL_NOTURNO": "",
            "excedente_apuracao_semanal": "",
            "deficit_apuracao_semanal": "",
            "excedente_apuracao_mensal": "",
            "deficit_apuracao_mensal": "",
            "key": "4b86698cacab4c2cbb87d63e"
        },
        {
            "NOME": "0020 SEG A SEX DAS 09:00 AS 16:00",
            "DESC_ESCALA": "0020 SEG A SEX DAS 09:00 AS 16:00",
            "COD": "19",
            "carga_horaria": "30",
            "tipo_escala": "",
            "TIPO": "SEMANAL",
            "JORNADAS": [
                "ece0835688304743a629996e",
                "ece0835688304743a629996e",
                "ece0835688304743a629996e",
                "ece0835688304743a629996e",
                "ece0835688304743a629996e",
                "ID_FOLGA",
                "ID_DSR"
            ],
            "dsr": {
                "ativo": "1",
                "dia_completo": "1",
                "desconto_valor_falta": "1",
                "apuracao": {
                    "semanal": "1"
                }
            },
            "TIPO_HORA_ADICIONAL": "",
            "TIPO_HORA_ADICIONAL_NOTURNO": "",
            "COD_ADICIONAL_NOTURNO": "",
            "excedente_apuracao_semanal": "",
            "deficit_apuracao_semanal": "",
            "excedente_apuracao_mensal": "",
            "deficit_apuracao_mensal": "",
            "key": "ac15f1e60c2748aabb698be3"
        }
    ],
    "jornadas": {
        "45c7dc2e8fa846848ba78135": {
            "NOME_JORNADA": "08:00 AS 18:00",
            "DESC_JORNADA": "",
            "HORAS_CONTRATUAIS": [
                "08:00",
                "12:30",
                "13:30",
                "18:00"
            ],
            "TRATAMENTO_EXPEDIENTE_EXTRA": "",
            "TRATAMENTO_ADICIONAL_PARA_PERIODO_DO_DIA": "",
            "HORAS_CONTRATUAIS_INTERVALO_EXTRA": [
                "",
                ""
            ],
            "FL_HORA_COMPENSAVEL": "1",
            "FL_ADICIONAL_NOTURNO_SOBRE_EXTRA": "",
            "FL_FATOR_POSTERIOR": "1",
            "FL_TRATAMENTO_CARGA_INFERIOR": "FALTA",
            "FL_TRATAMENTO_CARGA_SUPERIOR": "Hora Extra 50%",
            "PREASSINALA_SOMENTE_BATIDAS_PARES": true,
            "batida_automatica": [
                "1230",
                "1330"
            ],
            "PERIODOS": [
                {
                    "TM_HORA_INICIO": "0000",
                    "TM_HORA_FIM": "0800",
                    "DESC_TIPO_HORA": "Hora Extra 50%"
                },
                {
                    "TM_HORA_INICIO": "0800",
                    "TM_HORA_FIM": "1230",
                    "DESC_TIPO_HORA": "Expediente"
                },
                {
                    "TM_HORA_INICIO": "1230",
                    "TM_HORA_FIM": "1330",
                    "DESC_TIPO_HORA": "Hora Extra 50%"
                },
                {
                    "TM_HORA_INICIO": "1330",
                    "TM_HORA_FIM": "1800",
                    "DESC_TIPO_HORA": "Expediente"
                },
                {
                    "TM_HORA_INICIO": "1800",
                    "TM_HORA_FIM": "2400",
                    "DESC_TIPO_HORA": "Hora Extra 50%"
                }
            ],
            "TM_TOLERANCIA_CARGA_NEGATIVA": "0010",
            "TM_TOLERANCIA_CARGA_POSITIVA": "0010",
            "TM_INTINERE_ENTRADA": "",
            "TM_INTINERE_SAIDA": "",
            "TIPO_HORA_ADICIONAL": "Hora Extra 100%",
            "TIPO_HORA_ADICIONAL_NOTURNO": "Hora Extra 100%",
            "sem_expediente": null,
            "TM_HORA_INICIO": "0000",
            "TM_TOLERANCIA_ENTRADA_ANTECIPADA": null,
            "TM_TOLERANCIA_ENTRADA_TARDIA": null,
            "TM_TOLERANCIA_SAIDA_ANTECIPADA": null,
            "TM_TOLERANCIA_SAIDA_TARDIA": null,
            "key": "45c7dc2e8fa846848ba78135"
        },
        "be2d1897df73498db5d06db7": {
            "NOME_JORNADA": "08:00 AS 17:00",
            "DESC_JORNADA": "",
            "HORAS_CONTRATUAIS": [
                "08:00",
                "12:00",
                "13:00",
                "17:00"
            ],
            "TRATAMENTO_EXPEDIENTE_EXTRA": "",
            "TRATAMENTO_ADICIONAL_PARA_PERIODO_DO_DIA": "",
            "HORAS_CONTRATUAIS_INTERVALO_EXTRA": [
                "",
                ""
            ],
            "FL_HORA_COMPENSAVEL": "1",
            "FL_ADICIONAL_NOTURNO_SOBRE_EXTRA": "",
            "FL_FATOR_POSTERIOR": "1",
            "FL_TRATAMENTO_CARGA_INFERIOR": "FALTA",
            "FL_TRATAMENTO_CARGA_SUPERIOR": "Hora Extra 50%",
            "PREASSINALA_SOMENTE_BATIDAS_PARES": true,
            "batida_automatica": [
                "1200",
                "1300"
            ],
            "PERIODOS": [
                {
                    "TM_HORA_INICIO": "0000",
                    "TM_HORA_FIM": "0800",
                    "DESC_TIPO_HORA": "Hora Extra 50%"
                },
                {
                    "TM_HORA_INICIO": "0800",
                    "TM_HORA_FIM": "1200",
                    "DESC_TIPO_HORA": "Expediente"
                },
                {
                    "TM_HORA_INICIO": "1200",
                    "TM_HORA_FIM": "1300",
                    "DESC_TIPO_HORA": "Hora Extra 50%"
                },
                {
                    "TM_HORA_INICIO": "1300",
                    "TM_HORA_FIM": "1700",
                    "DESC_TIPO_HORA": "Expediente"
                },
                {
                    "TM_HORA_INICIO": "1700",
                    "TM_HORA_FIM": "2400",
                    "DESC_TIPO_HORA": "Hora Extra 50%"
                }
            ],
            "TM_TOLERANCIA_CARGA_NEGATIVA": "0010",
            "TM_TOLERANCIA_CARGA_POSITIVA": "0010",
            "TM_INTINERE_ENTRADA": "",
            "TM_INTINERE_SAIDA": "",
            "TIPO_HORA_ADICIONAL": "Hora Extra 100%",
            "TIPO_HORA_ADICIONAL_NOTURNO": "Hora Extra 100%",
            "sem_expediente": null,
            "TM_HORA_INICIO": "0000",
            "TM_TOLERANCIA_ENTRADA_ANTECIPADA": null,
            "TM_TOLERANCIA_ENTRADA_TARDIA": null,
            "TM_TOLERANCIA_SAIDA_ANTECIPADA": null,
            "TM_TOLERANCIA_SAIDA_TARDIA": null,
            "key": "be2d1897df73498db5d06db7"
        },
        "ID_DSR": {
            "NOME_JORNADA": "DSR",
            "key": "ID_DSR",
            "PERIODOS": [],
            "HORAS_CONTRATUAIS": []
        },
        "ID_FOLGA": {
            "NOME_JORNADA": "FOLGA",
            "key": "ID_FOLGA",
            "PERIODOS": [],
            "HORAS_CONTRATUAIS": []
        },
        "e4285448dbc24cf3b0c8e2c1": {
            "NOME_JORNADA": "08:00 AS 12:00",
            "DESC_JORNADA": "",
            "HORAS_CONTRATUAIS": [
                "08:00",
                "12:00"
            ],
            "TRATAMENTO_EXPEDIENTE_EXTRA": "",
            "TRATAMENTO_ADICIONAL_PARA_PERIODO_DO_DIA": "",
            "HORAS_CONTRATUAIS_INTERVALO_EXTRA": [
                "",
                ""
            ],
            "FL_HORA_COMPENSAVEL": "1",
            "FL_ADICIONAL_NOTURNO_SOBRE_EXTRA": "",
            "FL_FATOR_POSTERIOR": "1",
            "FL_TRATAMENTO_CARGA_INFERIOR": "FALTA",
            "FL_TRATAMENTO_CARGA_SUPERIOR": "Hora Extra 50%",
            "PREASSINALA_SOMENTE_BATIDAS_PARES": false,
            "batida_automatica": [],
            "PERIODOS": [
                {
                    "TM_HORA_INICIO": "0000",
                    "TM_HORA_FIM": "0800",
                    "DESC_TIPO_HORA": "Hora Extra 50%"
                },
                {
                    "TM_HORA_INICIO": "0800",
                    "TM_HORA_FIM": "1200",
                    "DESC_TIPO_HORA": "Expediente"
                },
                {
                    "TM_HORA_INICIO": "1200",
                    "TM_HORA_FIM": "2400",
                    "DESC_TIPO_HORA": "Hora Extra 50%"
                }
            ],
            "TM_TOLERANCIA_CARGA_NEGATIVA": "0010",
            "TM_TOLERANCIA_CARGA_POSITIVA": "0010",
            "TM_INTINERE_ENTRADA": "",
            "TM_INTINERE_SAIDA": "",
            "TIPO_HORA_ADICIONAL": "Hora Extra 100%",
            "TIPO_HORA_ADICIONAL_NOTURNO": "Hora Extra 100%",
            "sem_expediente": null,
            "TM_HORA_INICIO": "0000",
            "TM_TOLERANCIA_ENTRADA_ANTECIPADA": null,
            "TM_TOLERANCIA_ENTRADA_TARDIA": null,
            "TM_TOLERANCIA_SAIDA_ANTECIPADA": null,
            "TM_TOLERANCIA_SAIDA_TARDIA": null,
            "key": "e4285448dbc24cf3b0c8e2c1"
        },
        "f69879ac6f904fdf8e9d800e": {
            "NOME_JORNADA": "07:00 AS 19:00",
            "DESC_JORNADA": "",
            "HORAS_CONTRATUAIS": [
                "07:00",
                "12:30",
                "13:30",
                "19:00"
            ],
            "TRATAMENTO_EXPEDIENTE_EXTRA": "",
            "TRATAMENTO_ADICIONAL_PARA_PERIODO_DO_DIA": "",
            "HORAS_CONTRATUAIS_INTERVALO_EXTRA": [
                "",
                ""
            ],
            "FL_HORA_COMPENSAVEL": "1",
            "FL_ADICIONAL_NOTURNO_SOBRE_EXTRA": "",
            "FL_FATOR_POSTERIOR": "1",
            "FL_TRATAMENTO_CARGA_INFERIOR": "FALTA",
            "FL_TRATAMENTO_CARGA_SUPERIOR": "Hora Extra 50%",
            "PREASSINALA_SOMENTE_BATIDAS_PARES": true,
            "batida_automatica": [
                "1230",
                "1330"
            ],
            "PERIODOS": [
                {
                    "TM_HORA_INICIO": "0000",
                    "TM_HORA_FIM": "0700",
                    "DESC_TIPO_HORA": "Hora Extra 50%"
                },
                {
                    "TM_HORA_INICIO": "0700",
                    "TM_HORA_FIM": "1230",
                    "DESC_TIPO_HORA": "Expediente"
                },
                {
                    "TM_HORA_INICIO": "1230",
                    "TM_HORA_FIM": "1330",
                    "DESC_TIPO_HORA": "Hora Extra 50%"
                },
                {
                    "TM_HORA_INICIO": "1330",
                    "TM_HORA_FIM": "1900",
                    "DESC_TIPO_HORA": "Expediente"
                },
                {
                    "TM_HORA_INICIO": "1900",
                    "TM_HORA_FIM": "2400",
                    "DESC_TIPO_HORA": "Hora Extra 50%"
                }
            ],
            "TM_TOLERANCIA_CARGA_NEGATIVA": "0010",
            "TM_TOLERANCIA_CARGA_POSITIVA": "0010",
            "TM_INTINERE_ENTRADA": "",
            "TM_INTINERE_SAIDA": "",
            "TIPO_HORA_ADICIONAL": "Hora Extra 100%",
            "TIPO_HORA_ADICIONAL_NOTURNO": "Hora Extra 100%",
            "sem_expediente": null,
            "TM_HORA_INICIO": "0000",
            "TM_TOLERANCIA_ENTRADA_ANTECIPADA": null,
            "TM_TOLERANCIA_ENTRADA_TARDIA": null,
            "TM_TOLERANCIA_SAIDA_ANTECIPADA": null,
            "TM_TOLERANCIA_SAIDA_TARDIA": null,
            "key": "f69879ac6f904fdf8e9d800e"
        },
        "72d0c1ccc118472889c55f26": {
            "NOME_JORNADA": "12:00 AS 22:00",
            "DESC_JORNADA": "",
            "HORAS_CONTRATUAIS": [
                "12:00",
                "16:30",
                "17:30",
                "22:00"
            ],
            "TRATAMENTO_EXPEDIENTE_EXTRA": "",
            "TRATAMENTO_ADICIONAL_PARA_PERIODO_DO_DIA": "",
            "HORAS_CONTRATUAIS_INTERVALO_EXTRA": [
                "",
                ""
            ],
            "FL_HORA_COMPENSAVEL": "1",
            "FL_ADICIONAL_NOTURNO_SOBRE_EXTRA": "",
            "FL_FATOR_POSTERIOR": "1",
            "FL_TRATAMENTO_CARGA_INFERIOR": "FALTA",
            "FL_TRATAMENTO_CARGA_SUPERIOR": "Hora Extra 50%",
            "PREASSINALA_SOMENTE_BATIDAS_PARES": true,
            "batida_automatica": [
                "1630",
                "1730"
            ],
            "PERIODOS": [
                {
                    "TM_HORA_INICIO": "0000",
                    "TM_HORA_FIM": "1200",
                    "DESC_TIPO_HORA": "Hora Extra 50%"
                },
                {
                    "TM_HORA_INICIO": "1200",
                    "TM_HORA_FIM": "1630",
                    "DESC_TIPO_HORA": "Expediente"
                },
                {
                    "TM_HORA_INICIO": "1630",
                    "TM_HORA_FIM": "1730",
                    "DESC_TIPO_HORA": "Hora Extra 50%"
                },
                {
                    "TM_HORA_INICIO": "1730",
                    "TM_HORA_FIM": "2200",
                    "DESC_TIPO_HORA": "Expediente"
                },
                {
                    "TM_HORA_INICIO": "2200",
                    "TM_HORA_FIM": "2400",
                    "DESC_TIPO_HORA": "Hora Extra 50%"
                }
            ],
            "TM_TOLERANCIA_CARGA_NEGATIVA": "0010",
            "TM_TOLERANCIA_CARGA_POSITIVA": "0010",
            "TM_INTINERE_ENTRADA": "",
            "TM_INTINERE_SAIDA": "",
            "TIPO_HORA_ADICIONAL": "Hora Extra 100%",
            "TIPO_HORA_ADICIONAL_NOTURNO": "Hora Extra 100%",
            "sem_expediente": null,
            "TM_HORA_INICIO": "0000",
            "TM_TOLERANCIA_ENTRADA_ANTECIPADA": null,
            "TM_TOLERANCIA_ENTRADA_TARDIA": null,
            "TM_TOLERANCIA_SAIDA_ANTECIPADA": null,
            "TM_TOLERANCIA_SAIDA_TARDIA": null,
            "key": "72d0c1ccc118472889c55f26"
        },
        "b1d8a951b137400f92524984": {
            "NOME_JORNADA": "12:00 AS 21:00",
            "DESC_JORNADA": "",
            "HORAS_CONTRATUAIS": [
                "12:00",
                "16:00",
                "17:00",
                "21:00"
            ],
            "TRATAMENTO_EXPEDIENTE_EXTRA": "",
            "TRATAMENTO_ADICIONAL_PARA_PERIODO_DO_DIA": "",
            "HORAS_CONTRATUAIS_INTERVALO_EXTRA": [
                "",
                ""
            ],
            "FL_HORA_COMPENSAVEL": "1",
            "FL_ADICIONAL_NOTURNO_SOBRE_EXTRA": "",
            "FL_FATOR_POSTERIOR": "1",
            "FL_TRATAMENTO_CARGA_INFERIOR": "FALTA",
            "FL_TRATAMENTO_CARGA_SUPERIOR": "Hora Extra 50%",
            "PREASSINALA_SOMENTE_BATIDAS_PARES": true,
            "batida_automatica": [
                "1600",
                "1700"
            ],
            "PERIODOS": [
                {
                    "TM_HORA_INICIO": "0000",
                    "TM_HORA_FIM": "1200",
                    "DESC_TIPO_HORA": "Hora Extra 50%"
                },
                {
                    "TM_HORA_INICIO": "1200",
                    "TM_HORA_FIM": "1600",
                    "DESC_TIPO_HORA": "Expediente"
                },
                {
                    "TM_HORA_INICIO": "1600",
                    "TM_HORA_FIM": "1700",
                    "DESC_TIPO_HORA": "Hora Extra 50%"
                },
                {
                    "TM_HORA_INICIO": "1700",
                    "TM_HORA_FIM": "2100",
                    "DESC_TIPO_HORA": "Expediente"
                },
                {
                    "TM_HORA_INICIO": "2100",
                    "TM_HORA_FIM": "2400",
                    "DESC_TIPO_HORA": "Hora Extra 50%"
                }
            ],
            "TM_TOLERANCIA_CARGA_NEGATIVA": "0010",
            "TM_TOLERANCIA_CARGA_POSITIVA": "0010",
            "TM_INTINERE_ENTRADA": "",
            "TM_INTINERE_SAIDA": "",
            "TIPO_HORA_ADICIONAL": "Hora Extra 100%",
            "TIPO_HORA_ADICIONAL_NOTURNO": "Hora Extra 100%",
            "sem_expediente": null,
            "TM_HORA_INICIO": "0000",
            "TM_TOLERANCIA_ENTRADA_ANTECIPADA": null,
            "TM_TOLERANCIA_ENTRADA_TARDIA": null,
            "TM_TOLERANCIA_SAIDA_ANTECIPADA": null,
            "TM_TOLERANCIA_SAIDA_TARDIA": null,
            "key": "b1d8a951b137400f92524984"
        },
        "2722fcf35e3949839ddb8c7f": {
            "NOME_JORNADA": "07:00 AS 17:00",
            "DESC_JORNADA": "",
            "HORAS_CONTRATUAIS": [
                "07:00",
                "11:30",
                "12:30",
                "17:00"
            ],
            "TRATAMENTO_EXPEDIENTE_EXTRA": "",
            "TRATAMENTO_ADICIONAL_PARA_PERIODO_DO_DIA": "",
            "HORAS_CONTRATUAIS_INTERVALO_EXTRA": [
                "",
                ""
            ],
            "FL_HORA_COMPENSAVEL": "1",
            "FL_ADICIONAL_NOTURNO_SOBRE_EXTRA": "",
            "FL_FATOR_POSTERIOR": "1",
            "FL_TRATAMENTO_CARGA_INFERIOR": "FALTA",
            "FL_TRATAMENTO_CARGA_SUPERIOR": "Hora Extra 50%",
            "PREASSINALA_SOMENTE_BATIDAS_PARES": true,
            "batida_automatica": [
                "1130",
                "1230"
            ],
            "PERIODOS": [
                {
                    "TM_HORA_INICIO": "0000",
                    "TM_HORA_FIM": "0700",
                    "DESC_TIPO_HORA": "Hora Extra 50%"
                },
                {
                    "TM_HORA_INICIO": "0700",
                    "TM_HORA_FIM": "1130",
                    "DESC_TIPO_HORA": "Expediente"
                },
                {
                    "TM_HORA_INICIO": "1130",
                    "TM_HORA_FIM": "1230",
                    "DESC_TIPO_HORA": "Hora Extra 50%"
                },
                {
                    "TM_HORA_INICIO": "1230",
                    "TM_HORA_FIM": "1700",
                    "DESC_TIPO_HORA": "Expediente"
                },
                {
                    "TM_HORA_INICIO": "1700",
                    "TM_HORA_FIM": "2400",
                    "DESC_TIPO_HORA": "Hora Extra 50%"
                }
            ],
            "TM_TOLERANCIA_CARGA_NEGATIVA": "0010",
            "TM_TOLERANCIA_CARGA_POSITIVA": "0010",
            "TM_INTINERE_ENTRADA": "",
            "TM_INTINERE_SAIDA": "",
            "TIPO_HORA_ADICIONAL": "Hora Extra 100%",
            "TIPO_HORA_ADICIONAL_NOTURNO": "Hora Extra 100%",
            "sem_expediente": null,
            "TM_HORA_INICIO": "0000",
            "TM_TOLERANCIA_ENTRADA_ANTECIPADA": null,
            "TM_TOLERANCIA_ENTRADA_TARDIA": null,
            "TM_TOLERANCIA_SAIDA_ANTECIPADA": null,
            "TM_TOLERANCIA_SAIDA_TARDIA": null,
            "key": "2722fcf35e3949839ddb8c7f"
        },
        "f396ad3074fe46a49a038c02": {
            "NOME_JORNADA": "07:00 AS 16:00",
            "DESC_JORNADA": "",
            "HORAS_CONTRATUAIS": [
                "07:00",
                "11:00",
                "12:00",
                "16:00"
            ],
            "TRATAMENTO_EXPEDIENTE_EXTRA": "",
            "TRATAMENTO_ADICIONAL_PARA_PERIODO_DO_DIA": "",
            "HORAS_CONTRATUAIS_INTERVALO_EXTRA": [
                "",
                ""
            ],
            "FL_HORA_COMPENSAVEL": "1",
            "FL_ADICIONAL_NOTURNO_SOBRE_EXTRA": "",
            "FL_FATOR_POSTERIOR": "1",
            "FL_TRATAMENTO_CARGA_INFERIOR": "FALTA",
            "FL_TRATAMENTO_CARGA_SUPERIOR": "Hora Extra 50%",
            "PREASSINALA_SOMENTE_BATIDAS_PARES": true,
            "batida_automatica": [
                "1100",
                "1200"
            ],
            "PERIODOS": [
                {
                    "TM_HORA_INICIO": "0000",
                    "TM_HORA_FIM": "0700",
                    "DESC_TIPO_HORA": "Hora Extra 50%"
                },
                {
                    "TM_HORA_INICIO": "0700",
                    "TM_HORA_FIM": "1100",
                    "DESC_TIPO_HORA": "Expediente"
                },
                {
                    "TM_HORA_INICIO": "1100",
                    "TM_HORA_FIM": "1200",
                    "DESC_TIPO_HORA": "Hora Extra 50%"
                },
                {
                    "TM_HORA_INICIO": "1200",
                    "TM_HORA_FIM": "1600",
                    "DESC_TIPO_HORA": "Expediente"
                },
                {
                    "TM_HORA_INICIO": "1600",
                    "TM_HORA_FIM": "2400",
                    "DESC_TIPO_HORA": "Hora Extra 50%"
                }
            ],
            "TM_TOLERANCIA_CARGA_NEGATIVA": "0010",
            "TM_TOLERANCIA_CARGA_POSITIVA": "0010",
            "TM_INTINERE_ENTRADA": "",
            "TM_INTINERE_SAIDA": "",
            "TIPO_HORA_ADICIONAL": "Hora Extra 100%",
            "TIPO_HORA_ADICIONAL_NOTURNO": "Hora Extra 100%",
            "sem_expediente": null,
            "TM_HORA_INICIO": "0000",
            "TM_TOLERANCIA_ENTRADA_ANTECIPADA": null,
            "TM_TOLERANCIA_ENTRADA_TARDIA": null,
            "TM_TOLERANCIA_SAIDA_ANTECIPADA": null,
            "TM_TOLERANCIA_SAIDA_TARDIA": null,
            "key": "f396ad3074fe46a49a038c02"
        },
        "cf36cce7a0aa4d9d94bbe4ae": {
            "NOME_JORNADA": "10:00 AS 20:00",
            "DESC_JORNADA": "",
            "HORAS_CONTRATUAIS": [
                "10:00",
                "14:30",
                "15:30",
                "20:00"
            ],
            "TRATAMENTO_EXPEDIENTE_EXTRA": "",
            "TRATAMENTO_ADICIONAL_PARA_PERIODO_DO_DIA": "",
            "HORAS_CONTRATUAIS_INTERVALO_EXTRA": [
                "",
                ""
            ],
            "FL_HORA_COMPENSAVEL": "1",
            "FL_ADICIONAL_NOTURNO_SOBRE_EXTRA": "",
            "FL_FATOR_POSTERIOR": "1",
            "FL_TRATAMENTO_CARGA_INFERIOR": "FALTA",
            "FL_TRATAMENTO_CARGA_SUPERIOR": "Hora Extra 50%",
            "PREASSINALA_SOMENTE_BATIDAS_PARES": true,
            "batida_automatica": [
                "1430",
                "1530"
            ],
            "PERIODOS": [
                {
                    "TM_HORA_INICIO": "0000",
                    "TM_HORA_FIM": "1000",
                    "DESC_TIPO_HORA": "Hora Extra 50%"
                },
                {
                    "TM_HORA_INICIO": "1000",
                    "TM_HORA_FIM": "1430",
                    "DESC_TIPO_HORA": "Expediente"
                },
                {
                    "TM_HORA_INICIO": "1430",
                    "TM_HORA_FIM": "1530",
                    "DESC_TIPO_HORA": "Hora Extra 50%"
                },
                {
                    "TM_HORA_INICIO": "1530",
                    "TM_HORA_FIM": "2000",
                    "DESC_TIPO_HORA": "Expediente"
                },
                {
                    "TM_HORA_INICIO": "2000",
                    "TM_HORA_FIM": "2400",
                    "DESC_TIPO_HORA": "Hora Extra 50%"
                }
            ],
            "TM_TOLERANCIA_CARGA_NEGATIVA": "0010",
            "TM_TOLERANCIA_CARGA_POSITIVA": "0010",
            "TM_INTINERE_ENTRADA": "",
            "TM_INTINERE_SAIDA": "",
            "TIPO_HORA_ADICIONAL": "Hora Extra 100%",
            "TIPO_HORA_ADICIONAL_NOTURNO": "Hora Extra 100%",
            "sem_expediente": null,
            "TM_HORA_INICIO": "0000",
            "TM_TOLERANCIA_ENTRADA_ANTECIPADA": null,
            "TM_TOLERANCIA_ENTRADA_TARDIA": null,
            "TM_TOLERANCIA_SAIDA_ANTECIPADA": null,
            "TM_TOLERANCIA_SAIDA_TARDIA": null,
            "key": "cf36cce7a0aa4d9d94bbe4ae"
        },
        "47a8ee57211c4383996324c1": {
            "NOME_JORNADA": "10:00 AS 19:00",
            "DESC_JORNADA": "",
            "HORAS_CONTRATUAIS": [
                "10:00",
                "14:00",
                "15:00",
                "19:00"
            ],
            "TRATAMENTO_EXPEDIENTE_EXTRA": "",
            "TRATAMENTO_ADICIONAL_PARA_PERIODO_DO_DIA": "",
            "HORAS_CONTRATUAIS_INTERVALO_EXTRA": [
                "",
                ""
            ],
            "FL_HORA_COMPENSAVEL": "1",
            "FL_ADICIONAL_NOTURNO_SOBRE_EXTRA": "",
            "FL_FATOR_POSTERIOR": "1",
            "FL_TRATAMENTO_CARGA_INFERIOR": "FALTA",
            "FL_TRATAMENTO_CARGA_SUPERIOR": "Hora Extra 50%",
            "PREASSINALA_SOMENTE_BATIDAS_PARES": true,
            "batida_automatica": [
                "1400",
                "1500"
            ],
            "PERIODOS": [
                {
                    "TM_HORA_INICIO": "0000",
                    "TM_HORA_FIM": "1000",
                    "DESC_TIPO_HORA": "Hora Extra 50%"
                },
                {
                    "TM_HORA_INICIO": "1000",
                    "TM_HORA_FIM": "1400",
                    "DESC_TIPO_HORA": "Expediente"
                },
                {
                    "TM_HORA_INICIO": "1400",
                    "TM_HORA_FIM": "1500",
                    "DESC_TIPO_HORA": "Hora Extra 50%"
                },
                {
                    "TM_HORA_INICIO": "1500",
                    "TM_HORA_FIM": "1900",
                    "DESC_TIPO_HORA": "Expediente"
                },
                {
                    "TM_HORA_INICIO": "1900",
                    "TM_HORA_FIM": "2400",
                    "DESC_TIPO_HORA": "Hora Extra 50%"
                }
            ],
            "TM_TOLERANCIA_CARGA_NEGATIVA": "0010",
            "TM_TOLERANCIA_CARGA_POSITIVA": "0010",
            "TM_INTINERE_ENTRADA": "",
            "TM_INTINERE_SAIDA": "",
            "TIPO_HORA_ADICIONAL": "Hora Extra 100%",
            "TIPO_HORA_ADICIONAL_NOTURNO": "Hora Extra 100%",
            "sem_expediente": null,
            "TM_HORA_INICIO": "0000",
            "TM_TOLERANCIA_ENTRADA_ANTECIPADA": null,
            "TM_TOLERANCIA_ENTRADA_TARDIA": null,
            "TM_TOLERANCIA_SAIDA_ANTECIPADA": null,
            "TM_TOLERANCIA_SAIDA_TARDIA": null,
            "key": "47a8ee57211c4383996324c1"
        },
        "4a2157a3d89b4b4f91be4faf": {
            "NOME_JORNADA": "09:00 AS 19:00",
            "DESC_JORNADA": "",
            "HORAS_CONTRATUAIS": [
                "09:00",
                "13:30",
                "14:30",
                "19:00"
            ],
            "TRATAMENTO_EXPEDIENTE_EXTRA": "",
            "TRATAMENTO_ADICIONAL_PARA_PERIODO_DO_DIA": "",
            "HORAS_CONTRATUAIS_INTERVALO_EXTRA": [
                "",
                ""
            ],
            "FL_HORA_COMPENSAVEL": "1",
            "FL_ADICIONAL_NOTURNO_SOBRE_EXTRA": "",
            "FL_FATOR_POSTERIOR": "1",
            "FL_TRATAMENTO_CARGA_INFERIOR": "FALTA",
            "FL_TRATAMENTO_CARGA_SUPERIOR": "Hora Extra 50%",
            "PREASSINALA_SOMENTE_BATIDAS_PARES": true,
            "batida_automatica": [
                "1330",
                "1430"
            ],
            "PERIODOS": [
                {
                    "TM_HORA_INICIO": "0000",
                    "TM_HORA_FIM": "0900",
                    "DESC_TIPO_HORA": "Hora Extra 50%"
                },
                {
                    "TM_HORA_INICIO": "0900",
                    "TM_HORA_FIM": "1330",
                    "DESC_TIPO_HORA": "Expediente"
                },
                {
                    "TM_HORA_INICIO": "1330",
                    "TM_HORA_FIM": "1430",
                    "DESC_TIPO_HORA": "Hora Extra 50%"
                },
                {
                    "TM_HORA_INICIO": "1430",
                    "TM_HORA_FIM": "1900",
                    "DESC_TIPO_HORA": "Expediente"
                },
                {
                    "TM_HORA_INICIO": "1900",
                    "TM_HORA_FIM": "2400",
                    "DESC_TIPO_HORA": "Hora Extra 50%"
                }
            ],
            "TM_TOLERANCIA_CARGA_NEGATIVA": "0010",
            "TM_TOLERANCIA_CARGA_POSITIVA": "0010",
            "TM_INTINERE_ENTRADA": "",
            "TM_INTINERE_SAIDA": "",
            "TIPO_HORA_ADICIONAL": "Hora Extra 100%",
            "TIPO_HORA_ADICIONAL_NOTURNO": "Hora Extra 100%",
            "sem_expediente": null,
            "TM_HORA_INICIO": "0000",
            "TM_TOLERANCIA_ENTRADA_ANTECIPADA": null,
            "TM_TOLERANCIA_ENTRADA_TARDIA": null,
            "TM_TOLERANCIA_SAIDA_ANTECIPADA": null,
            "TM_TOLERANCIA_SAIDA_TARDIA": null,
            "key": "4a2157a3d89b4b4f91be4faf"
        },
        "5b0814e9c0c64b70ab6f45ed": {
            "NOME_JORNADA": "09:00 AS 18:00",
            "DESC_JORNADA": "",
            "HORAS_CONTRATUAIS": [
                "09:00",
                "13:00",
                "14:00",
                "18:00"
            ],
            "TRATAMENTO_EXPEDIENTE_EXTRA": "",
            "TRATAMENTO_ADICIONAL_PARA_PERIODO_DO_DIA": "",
            "HORAS_CONTRATUAIS_INTERVALO_EXTRA": [
                "",
                ""
            ],
            "FL_HORA_COMPENSAVEL": "1",
            "FL_ADICIONAL_NOTURNO_SOBRE_EXTRA": "",
            "FL_FATOR_POSTERIOR": "1",
            "FL_TRATAMENTO_CARGA_INFERIOR": "FALTA",
            "FL_TRATAMENTO_CARGA_SUPERIOR": "Hora Extra 50%",
            "PREASSINALA_SOMENTE_BATIDAS_PARES": true,
            "batida_automatica": [
                "1300",
                "1400"
            ],
            "PERIODOS": [
                {
                    "TM_HORA_INICIO": "0000",
                    "TM_HORA_FIM": "0900",
                    "DESC_TIPO_HORA": "Hora Extra 50%"
                },
                {
                    "TM_HORA_INICIO": "0900",
                    "TM_HORA_FIM": "1300",
                    "DESC_TIPO_HORA": "Expediente"
                },
                {
                    "TM_HORA_INICIO": "1300",
                    "TM_HORA_FIM": "1400",
                    "DESC_TIPO_HORA": "Hora Extra 50%"
                },
                {
                    "TM_HORA_INICIO": "1400",
                    "TM_HORA_FIM": "1800",
                    "DESC_TIPO_HORA": "Expediente"
                },
                {
                    "TM_HORA_INICIO": "1800",
                    "TM_HORA_FIM": "2400",
                    "DESC_TIPO_HORA": "Hora Extra 50%"
                }
            ],
            "TM_TOLERANCIA_CARGA_NEGATIVA": "0010",
            "TM_TOLERANCIA_CARGA_POSITIVA": "0010",
            "TM_INTINERE_ENTRADA": "",
            "TM_INTINERE_SAIDA": "",
            "TIPO_HORA_ADICIONAL": "Hora Extra 100%",
            "TIPO_HORA_ADICIONAL_NOTURNO": "Hora Extra 100%",
            "sem_expediente": null,
            "TM_HORA_INICIO": "0000",
            "TM_TOLERANCIA_ENTRADA_ANTECIPADA": null,
            "TM_TOLERANCIA_ENTRADA_TARDIA": null,
            "TM_TOLERANCIA_SAIDA_ANTECIPADA": null,
            "TM_TOLERANCIA_SAIDA_TARDIA": null,
            "key": "5b0814e9c0c64b70ab6f45ed"
        },
        "b3d5188a89fa4d62b8139c66": {
            "NOME_JORNADA": "13:40 AS 20:00",
            "DESC_JORNADA": "",
            "HORAS_CONTRATUAIS": [
                "13:40",
                "16:20",
                "17:20",
                "20:00"
            ],
            "TRATAMENTO_EXPEDIENTE_EXTRA": "",
            "TRATAMENTO_ADICIONAL_PARA_PERIODO_DO_DIA": "",
            "HORAS_CONTRATUAIS_INTERVALO_EXTRA": [
                "",
                ""
            ],
            "FL_HORA_COMPENSAVEL": "1",
            "FL_ADICIONAL_NOTURNO_SOBRE_EXTRA": "",
            "FL_FATOR_POSTERIOR": "1",
            "FL_TRATAMENTO_CARGA_INFERIOR": "FALTA",
            "FL_TRATAMENTO_CARGA_SUPERIOR": "Hora Extra 50%",
            "PREASSINALA_SOMENTE_BATIDAS_PARES": true,
            "batida_automatica": [
                "1620",
                "1720"
            ],
            "PERIODOS": [
                {
                    "TM_HORA_INICIO": "0000",
                    "TM_HORA_FIM": "1340",
                    "DESC_TIPO_HORA": "Hora Extra 50%"
                },
                {
                    "TM_HORA_INICIO": "1340",
                    "TM_HORA_FIM": "1620",
                    "DESC_TIPO_HORA": "Expediente"
                },
                {
                    "TM_HORA_INICIO": "1620",
                    "TM_HORA_FIM": "1720",
                    "DESC_TIPO_HORA": "Hora Extra 50%"
                },
                {
                    "TM_HORA_INICIO": "1720",
                    "TM_HORA_FIM": "2000",
                    "DESC_TIPO_HORA": "Expediente"
                },
                {
                    "TM_HORA_INICIO": "2000",
                    "TM_HORA_FIM": "2400",
                    "DESC_TIPO_HORA": "Hora Extra 50%"
                }
            ],
            "TM_TOLERANCIA_CARGA_NEGATIVA": "0010",
            "TM_TOLERANCIA_CARGA_POSITIVA": "0010",
            "TM_INTINERE_ENTRADA": "",
            "TM_INTINERE_SAIDA": "",
            "TIPO_HORA_ADICIONAL": "Hora Extra 100%",
            "TIPO_HORA_ADICIONAL_NOTURNO": "Hora Extra 100%",
            "sem_expediente": null,
            "TM_HORA_INICIO": "0000",
            "TM_TOLERANCIA_ENTRADA_ANTECIPADA": null,
            "TM_TOLERANCIA_ENTRADA_TARDIA": null,
            "TM_TOLERANCIA_SAIDA_ANTECIPADA": null,
            "TM_TOLERANCIA_SAIDA_TARDIA": null,
            "key": "b3d5188a89fa4d62b8139c66"
        },
        "0e471c11bd0544c1bfdbaf05": {
            "NOME_JORNADA": "15:40 AS 22:00",
            "DESC_JORNADA": "",
            "HORAS_CONTRATUAIS": [
                "15:40",
                "18:20",
                "19:20",
                "22:00"
            ],
            "TRATAMENTO_EXPEDIENTE_EXTRA": "",
            "TRATAMENTO_ADICIONAL_PARA_PERIODO_DO_DIA": "",
            "HORAS_CONTRATUAIS_INTERVALO_EXTRA": [
                "",
                ""
            ],
            "FL_HORA_COMPENSAVEL": "1",
            "FL_ADICIONAL_NOTURNO_SOBRE_EXTRA": "",
            "FL_FATOR_POSTERIOR": "1",
            "FL_TRATAMENTO_CARGA_INFERIOR": "FALTA",
            "FL_TRATAMENTO_CARGA_SUPERIOR": "Hora Extra 50%",
            "PREASSINALA_SOMENTE_BATIDAS_PARES": true,
            "batida_automatica": [
                "1820",
                "1920"
            ],
            "PERIODOS": [
                {
                    "TM_HORA_INICIO": "0000",
                    "TM_HORA_FIM": "1540",
                    "DESC_TIPO_HORA": "Hora Extra 50%"
                },
                {
                    "TM_HORA_INICIO": "1540",
                    "TM_HORA_FIM": "1820",
                    "DESC_TIPO_HORA": "Expediente"
                },
                {
                    "TM_HORA_INICIO": "1820",
                    "TM_HORA_FIM": "1920",
                    "DESC_TIPO_HORA": "Hora Extra 50%"
                },
                {
                    "TM_HORA_INICIO": "1920",
                    "TM_HORA_FIM": "2200",
                    "DESC_TIPO_HORA": "Expediente"
                },
                {
                    "TM_HORA_INICIO": "2200",
                    "TM_HORA_FIM": "2400",
                    "DESC_TIPO_HORA": "Hora Extra 50%"
                }
            ],
            "TM_TOLERANCIA_CARGA_NEGATIVA": "0010",
            "TM_TOLERANCIA_CARGA_POSITIVA": "0010",
            "TM_INTINERE_ENTRADA": "",
            "TM_INTINERE_SAIDA": "",
            "TIPO_HORA_ADICIONAL": "Hora Extra 100%",
            "TIPO_HORA_ADICIONAL_NOTURNO": "Hora Extra 100%",
            "sem_expediente": null,
            "TM_HORA_INICIO": "0000",
            "TM_TOLERANCIA_ENTRADA_ANTECIPADA": null,
            "TM_TOLERANCIA_ENTRADA_TARDIA": null,
            "TM_TOLERANCIA_SAIDA_ANTECIPADA": null,
            "TM_TOLERANCIA_SAIDA_TARDIA": null,
            "key": "0e471c11bd0544c1bfdbaf05"
        },
        "b6c463aeca3f480aa51e0867": {
            "NOME_JORNADA": "06:00 AS 16:00",
            "DESC_JORNADA": "",
            "HORAS_CONTRATUAIS": [
                "06:00",
                "10:30",
                "11:30",
                "16:00"
            ],
            "TRATAMENTO_EXPEDIENTE_EXTRA": "",
            "TRATAMENTO_ADICIONAL_PARA_PERIODO_DO_DIA": "",
            "HORAS_CONTRATUAIS_INTERVALO_EXTRA": [
                "",
                ""
            ],
            "FL_HORA_COMPENSAVEL": "1",
            "FL_ADICIONAL_NOTURNO_SOBRE_EXTRA": "",
            "FL_FATOR_POSTERIOR": "1",
            "FL_TRATAMENTO_CARGA_INFERIOR": "FALTA",
            "FL_TRATAMENTO_CARGA_SUPERIOR": "Hora Extra 50%",
            "PREASSINALA_SOMENTE_BATIDAS_PARES": true,
            "batida_automatica": [
                "1030",
                "1130"
            ],
            "PERIODOS": [
                {
                    "TM_HORA_INICIO": "0000",
                    "TM_HORA_FIM": "0600",
                    "DESC_TIPO_HORA": "Hora Extra 50%"
                },
                {
                    "TM_HORA_INICIO": "0600",
                    "TM_HORA_FIM": "1030",
                    "DESC_TIPO_HORA": "Expediente"
                },
                {
                    "TM_HORA_INICIO": "1030",
                    "TM_HORA_FIM": "1130",
                    "DESC_TIPO_HORA": "Hora Extra 50%"
                },
                {
                    "TM_HORA_INICIO": "1130",
                    "TM_HORA_FIM": "1600",
                    "DESC_TIPO_HORA": "Expediente"
                },
                {
                    "TM_HORA_INICIO": "1600",
                    "TM_HORA_FIM": "2400",
                    "DESC_TIPO_HORA": "Hora Extra 50%"
                }
            ],
            "TM_TOLERANCIA_CARGA_NEGATIVA": "0010",
            "TM_TOLERANCIA_CARGA_POSITIVA": "0010",
            "TM_INTINERE_ENTRADA": "",
            "TM_INTINERE_SAIDA": "",
            "TIPO_HORA_ADICIONAL": "Hora Extra 100%",
            "TIPO_HORA_ADICIONAL_NOTURNO": "Hora Extra 100%",
            "sem_expediente": null,
            "TM_HORA_INICIO": "0000",
            "TM_TOLERANCIA_ENTRADA_ANTECIPADA": null,
            "TM_TOLERANCIA_ENTRADA_TARDIA": null,
            "TM_TOLERANCIA_SAIDA_ANTECIPADA": null,
            "TM_TOLERANCIA_SAIDA_TARDIA": null,
            "key": "b6c463aeca3f480aa51e0867"
        },
        "64ffacafeb984663a0b9bbdc": {
            "NOME_JORNADA": "06:00 AS 15:00",
            "DESC_JORNADA": "",
            "HORAS_CONTRATUAIS": [
                "06:00",
                "10:00",
                "11:00",
                "15:00"
            ],
            "TRATAMENTO_EXPEDIENTE_EXTRA": "",
            "TRATAMENTO_ADICIONAL_PARA_PERIODO_DO_DIA": "",
            "HORAS_CONTRATUAIS_INTERVALO_EXTRA": [
                "",
                ""
            ],
            "FL_HORA_COMPENSAVEL": "1",
            "FL_ADICIONAL_NOTURNO_SOBRE_EXTRA": "",
            "FL_FATOR_POSTERIOR": "1",
            "FL_TRATAMENTO_CARGA_INFERIOR": "FALTA",
            "FL_TRATAMENTO_CARGA_SUPERIOR": "Hora Extra 50%",
            "PREASSINALA_SOMENTE_BATIDAS_PARES": true,
            "batida_automatica": [
                "1000",
                "1100"
            ],
            "PERIODOS": [
                {
                    "TM_HORA_INICIO": "0000",
                    "TM_HORA_FIM": "0600",
                    "DESC_TIPO_HORA": "Hora Extra 50%"
                },
                {
                    "TM_HORA_INICIO": "0600",
                    "TM_HORA_FIM": "1000",
                    "DESC_TIPO_HORA": "Expediente"
                },
                {
                    "TM_HORA_INICIO": "1000",
                    "TM_HORA_FIM": "1100",
                    "DESC_TIPO_HORA": "Hora Extra 50%"
                },
                {
                    "TM_HORA_INICIO": "1100",
                    "TM_HORA_FIM": "1500",
                    "DESC_TIPO_HORA": "Expediente"
                },
                {
                    "TM_HORA_INICIO": "1500",
                    "TM_HORA_FIM": "2400",
                    "DESC_TIPO_HORA": "Hora Extra 50%"
                }
            ],
            "TM_TOLERANCIA_CARGA_NEGATIVA": "0010",
            "TM_TOLERANCIA_CARGA_POSITIVA": "0010",
            "TM_INTINERE_ENTRADA": "",
            "TM_INTINERE_SAIDA": "",
            "TIPO_HORA_ADICIONAL": "Hora Extra 100%",
            "TIPO_HORA_ADICIONAL_NOTURNO": "Hora Extra 100%",
            "sem_expediente": null,
            "TM_HORA_INICIO": "0000",
            "TM_TOLERANCIA_ENTRADA_ANTECIPADA": null,
            "TM_TOLERANCIA_ENTRADA_TARDIA": null,
            "TM_TOLERANCIA_SAIDA_ANTECIPADA": null,
            "TM_TOLERANCIA_SAIDA_TARDIA": null,
            "key": "64ffacafeb984663a0b9bbdc"
        },
        "6d80ebee92d04220ba66ed63": {
            "NOME_JORNADA": "14:00 AS 22:00",
            "DESC_JORNADA": "",
            "HORAS_CONTRATUAIS": [
                "14:00",
                "17:30",
                "18:30",
                "22:00"
            ],
            "TRATAMENTO_EXPEDIENTE_EXTRA": "",
            "TRATAMENTO_ADICIONAL_PARA_PERIODO_DO_DIA": "",
            "HORAS_CONTRATUAIS_INTERVALO_EXTRA": [
                "",
                ""
            ],
            "FL_HORA_COMPENSAVEL": "1",
            "FL_ADICIONAL_NOTURNO_SOBRE_EXTRA": "",
            "FL_FATOR_POSTERIOR": "1",
            "FL_TRATAMENTO_CARGA_INFERIOR": "FALTA",
            "FL_TRATAMENTO_CARGA_SUPERIOR": "Hora Extra 50%",
            "PREASSINALA_SOMENTE_BATIDAS_PARES": true,
            "batida_automatica": [
                "1730",
                "1830"
            ],
            "PERIODOS": [
                {
                    "TM_HORA_INICIO": "0000",
                    "TM_HORA_FIM": "1400",
                    "DESC_TIPO_HORA": "Hora Extra 50%"
                },
                {
                    "TM_HORA_INICIO": "1400",
                    "TM_HORA_FIM": "1730",
                    "DESC_TIPO_HORA": "Expediente"
                },
                {
                    "TM_HORA_INICIO": "1730",
                    "TM_HORA_FIM": "1830",
                    "DESC_TIPO_HORA": "Hora Extra 50%"
                },
                {
                    "TM_HORA_INICIO": "1830",
                    "TM_HORA_FIM": "2200",
                    "DESC_TIPO_HORA": "Expediente"
                },
                {
                    "TM_HORA_INICIO": "2200",
                    "TM_HORA_FIM": "2400",
                    "DESC_TIPO_HORA": "Hora Extra 50%"
                }
            ],
            "TM_TOLERANCIA_CARGA_NEGATIVA": "0010",
            "TM_TOLERANCIA_CARGA_POSITIVA": "0010",
            "TM_INTINERE_ENTRADA": "",
            "TM_INTINERE_SAIDA": "",
            "TIPO_HORA_ADICIONAL": "Hora Extra 100%",
            "TIPO_HORA_ADICIONAL_NOTURNO": "Hora Extra 100%",
            "sem_expediente": null,
            "TM_HORA_INICIO": "0000",
            "TM_TOLERANCIA_ENTRADA_ANTECIPADA": null,
            "TM_TOLERANCIA_ENTRADA_TARDIA": null,
            "TM_TOLERANCIA_SAIDA_ANTECIPADA": null,
            "TM_TOLERANCIA_SAIDA_TARDIA": null,
            "key": "6d80ebee92d04220ba66ed63"
        },
        "f22d70a867584cfdb6a5bc30": {
            "NOME_JORNADA": "22:00 AS 06:00",
            "DESC_JORNADA": "",
            "HORAS_CONTRATUAIS": [
                "22:00",
                "01:30",
                "02:30",
                "06:00"
            ],
            "TRATAMENTO_EXPEDIENTE_EXTRA": "",
            "TRATAMENTO_ADICIONAL_PARA_PERIODO_DO_DIA": "",
            "HORAS_CONTRATUAIS_INTERVALO_EXTRA": [
                "",
                ""
            ],
            "FL_HORA_COMPENSAVEL": "1",
            "FL_ADICIONAL_NOTURNO_SOBRE_EXTRA": "",
            "FL_FATOR_POSTERIOR": "1",
            "FL_TRATAMENTO_CARGA_INFERIOR": "FALTA",
            "FL_TRATAMENTO_CARGA_SUPERIOR": "Hora Extra 50%",
            "PREASSINALA_SOMENTE_BATIDAS_PARES": true,
            "batida_automatica": [
                "0130",
                "0230"
            ],
            "PERIODOS": [
                {
                    "TM_HORA_INICIO": "0000",
                    "TM_HORA_FIM": "2200",
                    "DESC_TIPO_HORA": "Hora Extra 50%"
                },
                {
                    "TM_HORA_INICIO": "2200",
                    "TM_HORA_FIM": "0130",
                    "DESC_TIPO_HORA": "Expediente"
                },
                {
                    "TM_HORA_INICIO": "0130",
                    "TM_HORA_FIM": "0230",
                    "DESC_TIPO_HORA": "Hora Extra 50%"
                },
                {
                    "TM_HORA_INICIO": "0230",
                    "TM_HORA_FIM": "0600",
                    "DESC_TIPO_HORA": "Expediente"
                },
                {
                    "TM_HORA_INICIO": "0600",
                    "TM_HORA_FIM": "2400",
                    "DESC_TIPO_HORA": "Hora Extra 50%"
                }
            ],
            "TM_TOLERANCIA_CARGA_NEGATIVA": "0010",
            "TM_TOLERANCIA_CARGA_POSITIVA": "0010",
            "TM_INTINERE_ENTRADA": "",
            "TM_INTINERE_SAIDA": "",
            "TIPO_HORA_ADICIONAL": "Hora Extra 100%",
            "TIPO_HORA_ADICIONAL_NOTURNO": "Hora Extra 100%",
            "sem_expediente": null,
            "TM_HORA_INICIO": "0000",
            "TM_TOLERANCIA_ENTRADA_ANTECIPADA": null,
            "TM_TOLERANCIA_ENTRADA_TARDIA": null,
            "TM_TOLERANCIA_SAIDA_ANTECIPADA": null,
            "TM_TOLERANCIA_SAIDA_TARDIA": null,
            "key": "f22d70a867584cfdb6a5bc30"
        },
        "ece0835688304743a629996e": {
            "NOME_JORNADA": "09:00 AS 16:00",
            "DESC_JORNADA": "",
            "HORAS_CONTRATUAIS": [
                "09:00",
                "12:00",
                "13:00",
                "16:00"
            ],
            "TRATAMENTO_EXPEDIENTE_EXTRA": "",
            "TRATAMENTO_ADICIONAL_PARA_PERIODO_DO_DIA": "",
            "HORAS_CONTRATUAIS_INTERVALO_EXTRA": [
                "",
                ""
            ],
            "FL_HORA_COMPENSAVEL": "1",
            "FL_ADICIONAL_NOTURNO_SOBRE_EXTRA": "",
            "FL_FATOR_POSTERIOR": "1",
            "FL_TRATAMENTO_CARGA_INFERIOR": "FALTA",
            "FL_TRATAMENTO_CARGA_SUPERIOR": "Hora Extra 50%",
            "PREASSINALA_SOMENTE_BATIDAS_PARES": true,
            "batida_automatica": [
                "1200",
                "1300"
            ],
            "PERIODOS": [
                {
                    "TM_HORA_INICIO": "0000",
                    "TM_HORA_FIM": "0900",
                    "DESC_TIPO_HORA": "Hora Extra 50%"
                },
                {
                    "TM_HORA_INICIO": "0900",
                    "TM_HORA_FIM": "1200",
                    "DESC_TIPO_HORA": "Expediente"
                },
                {
                    "TM_HORA_INICIO": "1200",
                    "TM_HORA_FIM": "1300",
                    "DESC_TIPO_HORA": "Hora Extra 50%"
                },
                {
                    "TM_HORA_INICIO": "1300",
                    "TM_HORA_FIM": "1600",
                    "DESC_TIPO_HORA": "Expediente"
                },
                {
                    "TM_HORA_INICIO": "1600",
                    "TM_HORA_FIM": "2400",
                    "DESC_TIPO_HORA": "Hora Extra 50%"
                }
            ],
            "TM_TOLERANCIA_CARGA_NEGATIVA": "0010",
            "TM_TOLERANCIA_CARGA_POSITIVA": "0010",
            "TM_INTINERE_ENTRADA": "",
            "TM_INTINERE_SAIDA": "",
            "TIPO_HORA_ADICIONAL": "Hora Extra 100%",
            "TIPO_HORA_ADICIONAL_NOTURNO": "Hora Extra 100%",
            "sem_expediente": null,
            "TM_HORA_INICIO": "0000",
            "TM_TOLERANCIA_ENTRADA_ANTECIPADA": null,
            "TM_TOLERANCIA_ENTRADA_TARDIA": null,
            "TM_TOLERANCIA_SAIDA_ANTECIPADA": null,
            "TM_TOLERANCIA_SAIDA_TARDIA": null,
            "key": "ece0835688304743a629996e"
        }
    },
    "horas_adicionais": []
}